render_engine_microblog/__init__.py
render_engine_microblog/collection.py
render_engine_microblog/themes.py
render_engine_microblog/templates/microblog.html
render_engine_microblog/templates/microblog_post.html
render_engine_microblog-2024.1.1.dist-info/LICENSE.md
render_engine_microblog-2024.1.1.dist-info/METADATA
render_engine_microblog-2024.1.1.dist-info/WHEEL
render_engine_microblog-2024.1.1.dist-info/top_level.txt
render_engine_microblog-2024.1.1.dist-info/RECORD
