Metadata-Version: 2.1
Name: render_engine_microblog
Version: 2024.1.1
Summary: Microblog Parser and Collection for Render Engine
Project-URL: homepage, https://github.com/kjaymiller/render_engine_microblog/
Project-URL: repository, https://github.com/kjaymiller/render_engine_microblog/
License-File: LICENSE.md
Requires-Dist: render-engine >=2024.1.1a2
Requires-Dist: jinja2
Requires-Dist: render-engine-markdown
Provides-Extra: dev
Requires-Dist: pytest ; extra == 'dev'
Requires-Dist: pytest-cov ; extra == 'dev'
Requires-Dist: gazpacho ; extra == 'dev'
Requires-Dist: ruff ; extra == 'dev'
